SpongeExt/__init__.py
SpongeExt/backends/__init__.py
SpongeExt/backends/backend/__init__.py
SpongeExt/backends/backend/base.py
SpongeExt/backends/backend/cuda.py
SpongeExt/backends/backend/data.py
SpongeExt/backends/backend/mindspore_ascend_ops.py
SpongeExt/backends/backend/mindspore_gpu_ops.py
SpongeExt/backends/backend/nn.py
SpongeExt/backends/backend/optim.py
SpongeExt/backends/backend/pytorch_ascend_ops.py
SpongeExt/backends/backend/pytorch_gpu_ops.py
SpongeExt/pysages/__init__.py
SpongeExt/pysages/meta.py
SpongeExt/pysages/plot_cv.py
SpongeExt/pysages/sink_meta.py
SpongeExt-1.3.dist-info/LICENSE
SpongeExt-1.3.dist-info/METADATA
SpongeExt-1.3.dist-info/WHEEL
SpongeExt-1.3.dist-info/top_level.txt
SpongeExt-1.3.dist-info/RECORD
