Metadata-Version: 2.1
Name: SpongeExt
Version: 1.3
Summary: Sponge Extension For Enhanced Sampling
Home-page: https://gitee.com/dechin/sponge-ext
Author: Dechin CHEN
Author-email: dechin.phy@gmail.com
License: Apache 2.0 Licence
Platform: any
License-File: LICENSE
Requires-Dist: numpy
